sqlalchemy_searchable/__init__.py
sqlalchemy_searchable/expressions.sql
sqlalchemy_searchable/vectorizers.py
sqlalchemy_searchable-2.0.0.dist-info/METADATA
sqlalchemy_searchable-2.0.0.dist-info/WHEEL
sqlalchemy_searchable-2.0.0.dist-info/licenses/LICENSE
sqlalchemy_searchable-2.0.0.dist-info/RECORD
